[
    {
        "axial_category": "Multi\u2011dimensional assessment of relationship quality",
        "index": 0,
        "trace": [
            {
                "rung": "none",
                "note": "no empty slots"
            }
        ]
    },
    {
        "axial_category": "Emotional connection and compassion",
        "index": 1,
        "trace": [
            {
                "rung": "none",
                "note": "no empty slots"
            }
        ]
    },
    {
        "axial_category": "Communication patterns and conflict management",
        "index": 2,
        "trace": [
            {
                "rung": "none",
                "note": "no empty slots"
            }
        ]
    },
    {
        "axial_category": "Role division and separate lives",
        "index": 3,
        "trace": [
            {
                "rung": "none",
                "note": "no empty slots"
            }
        ]
    },
    {
        "axial_category": "Conceptualizations of love",
        "index": 4,
        "trace": [
            {
                "rung": "none",
                "note": "no empty slots"
            }
        ]
    },
    {
        "axial_category": "Sexual intimacy and desire",
        "index": 5,
        "trace": [
            {
                "rung": "none",
                "note": "no empty slots"
            }
        ]
    },
    {
        "axial_category": "Trust, safety and reliability",
        "index": 6,
        "trace": [
            {
                "rung": "none",
                "note": "no empty slots"
            }
        ]
    },
    {
        "axial_category": "Social comparison and external benchmarks",
        "index": 7,
        "trace": [
            {
                "rung": "none",
                "note": "no empty slots"
            }
        ]
    },
    {
        "axial_category": "Life\u2011stage transitions and personal change",
        "index": 8,
        "trace": [
            {
                "rung": "none",
                "note": "no empty slots"
            }
        ]
    },
    {
        "axial_category": "Partner support and caregiving",
        "index": 9,
        "trace": [
            {
                "rung": "none",
                "note": "no empty slots"
            }
        ]
    },
    {
        "axial_category": "Communication as core relationship quality factor",
        "index": 10,
        "trace": [
            {
                "rung": "none",
                "note": "no empty slots"
            }
        ]
    }
]